skychart/__init__.py
skychart/constellations.py
skychart/hipparcos.py
skychart/load_data.py
skychart/plotting.py
skychart/tools.py
skychart-0.0.3.dist-info/LICENSE.txt
skychart-0.0.3.dist-info/METADATA
skychart-0.0.3.dist-info/WHEEL
skychart-0.0.3.dist-info/top_level.txt
skychart-0.0.3.dist-info/RECORD
