Metadata-Version: 2.1
Name: skychart
Version: 0.0.3
Summary: A python package for creating star charts
Home-page: https://github.com/behrouzz/skychart
Author: Behrouz Safari
Author-email: behrouz.safari@gmail.com
License: MIT
Platform: UNKNOWN
Classifier: Programming Language :: Python :: 3
Classifier: License :: OSI Approved :: MIT License
Classifier: Operating System :: OS Independent
Requires-Python: >=3.4
License-File: LICENSE.txt
Requires-Dist: numpy
Requires-Dist: pandas
Requires-Dist: matplotlib
